{
  "name": "Better GitHub Theme (BGT)",
  "dark": true,
  "author": "Maximus019",
  "editorScheme": "BGT.icls",
  "colors": {
    "mainColor": "#0D1117",
    "tab.background.hovered": "#161B22",
    "tab.background.default": "#0D1117",
    "popup.tab.background.default": "#0D1117",
    "foreground": "#C9D1D9",
    "activeTabBackground": "#0D1117",
    "activeTabForeground": "#C9D1D9",
    "hoverColor": "#161B22",
    "terminalBackground": "mainColor",
    "terminalForeground": "foreground",
    "topWindowLineBackground": "mainColor",
    "topWindowLineForeground": "foreground"
  },
  "ui": {
    "Panel.background": "mainColor",
    "Panel.foreground": "foreground",
    "ToolBar.background": "mainColor",
    "ToolBar.foreground": "foreground",
    "EditorTabs.background": "mainColor",
    "EditorTabs.foreground": "foreground",
    "Menu.background": "mainColor",
    "Menu.foreground": "foreground",
    "MenuBar.foreground": "foreground",
    "MenuItem.background": "mainColor",
    "MenuItem.foreground": "foreground",
    "MenuItem.hoverBackground": "hoverColor",
    "ProjectView.background": "mainColor",
    "ProjectView.foreground": "foreground",
    "NavBar.background": "mainColor",
    "NavBar.foreground": "foreground",
    "NavBar.hoverBackground": "hoverColor",
    "PopupMenu.background": "mainColor",
    "PopupMenu.foreground": "foreground",
    "ContextMenu.background": "mainColor",
    "ContextMenu.foreground": "foreground",
    "SidePanel.background": "mainColor",
    "SidePanel.foreground": "foreground",
    "ToolWindow.background": "mainColor",
    "ToolWindow.foreground": "foreground",
    "Button.background": "mainColor",
    "Button.foreground": "foreground",
    "Button.hoverBackground": "hoverColor",
    "Button.pressedBackground": "pressedColor",
    "CheckBox.background": "mainColor",
    "CheckBox.foreground": "foreground",
    "ComboBox.background": "mainColor",
    "ComboBox.foreground": "foreground",
    "ComboBox.buttonBackground": "buttonColor",
    "ComboBox.buttonForeground": "buttonForeground",
    "Dialog.background": "mainColor",
    "Dialog.foreground": "foreground",
    "ToolWindow.HeaderTab.selectedBackground": "mainColor",
    "EditorTabs.selectedBackground": "selectedColor",
    "EditorTabs.selectedForeground": "selectedForeground",
    "List.background": "mainColor",
    "List.foreground": "foreground",
    "List.selectionBackground": "selectionColor",
    "List.selectionForeground": "selectionForeground",
    "Notification.background": "mainColor",
    "Notification.foreground": "foreground",
    "Notification.errorBackground": "errorColor",
    "Notification.warningBackground": "warningColor",
    "Notification.infoBackground": "infoColor",
    "ProgressBar.background": "mainColor",
    "ProgressBar.foreground": "foreground",
    "ScrollBar.background": "mainColor",
    "terminalBackground": "mainColor",
    "terminalForeground": "foreground",
    "Terminal.lineBackground": "mainColor",
    "Terminal.lineForeground": "foreground",
    "StatusBar.background": "mainColor",
    "StatusBar.foreground": "foreground",
    "ToolWindowBar.background": "mainColor",
    "ToolWindowBar.foreground": "foreground",
    "ScrollBar.foreground": "foreground",
    "Table.background": "mainColor",
    "Table.foreground": "foreground",
    "Table.selectionBackground": "selectionColor",
    "Table.selectionForeground": "selectionForeground",
    "TextField.background": "mainColor",
    "TextField.foreground": "foreground",
    "ToolTip.background": "mainColor",
    "ToolTip.foreground": "foreground",
    "Tree.background": "mainColor",
    "Tree.foreground": "foreground",
    "Tree.selectionBackground": "selectionColor",
    "Tree.selectionForeground": "selectionForeground",
    "ActionButton.background": "mainColor",
    "ActionButton.foreground": "foreground",
    "ActionButton.hoverBackground": "hoverColor",
    "ActionButton.pressedBackground": "pressedColor",
    "Breadcrumbs.background": "mainColor",
    "Breadcrumbs.foreground": "foreground",
    "Breadcrumbs.selectionBackground": "selectionColor",
    "Breadcrumbs.selectionForeground": "selectionForeground",
    "CompletionPopup.background": "mainColor",
    "CompletionPopup.foreground": "foreground",
    "DebuggerTabs.background": "mainColor",
    "DebuggerTabs.foreground": "foreground",
    "DebuggerTabs.selectedBackground": "selectedColor",
    "DebuggerTabs.selectedForeground": "selectedForeground",
    "DragAndDrop.background": "mainColor",
    "DragAndDrop.foreground": "foreground",
    "EditorPane.background": "mainColor",
    "EditorPane.foreground": "foreground",
    "FocusBorder.color": "borderColor",
    "HeaderPanel.background": "mainColor",
    "HeaderPanel.foreground": "foreground",
    "Hyperlink.foreground": "linkColor",
    "Hyperlink.visitedForeground": "visitedLinkColor",
    "Notification.MoreButton.background": "mainColor",
    "Notification.MoreButton.foreground": "foreground",
    "Notification.MoreButton.hoverBackground": "hoverColor",
    "Notification.MoreButton.pressedBackground": "pressedColor",
    "Popup.Advertiser.background": "mainColor",
    "Popup.Advertiser.foreground": "foreground",
    "SearchEverywhere.background": "mainColor",
    "SearchEverywhere.foreground": "foreground",
    "SearchEverywhere.selectionBackground": "selectionColor",
    "SearchEverywhere.selectionForeground": "selectionForeground",
    "Separator.foreground": "separatorColor",
    "TabbedPane.background": "mainColor",
    "TabbedPane.foreground": "foreground",
    "TabbedPane.selectedBackground": "selectedColor",
    "TabbedPane.selectedForeground": "selectedForeground",
    "TextArea.background": "mainColor",
    "TextArea.foreground": "foreground",
    "TextPane.background": "mainColor",
    "TextPane.foreground": "foreground",
    "TitlePane.background": "mainColor",
    "TitlePane.foreground": "foreground",
    "TitlePane.inactiveBackground": "mainColor",
    "TitlePane.inactiveForeground": "foreground",
    "ToolBar.separatorColor": "separatorColor",
    "ToolWindow.Header.background": "mainColor",
    "ToolWindow": {
      "Header.background": "mainColor",
      "Header.foreground": "foreground",
      "HeaderTab.selectedBackground": "mainColor",
      "HeaderTab.selectedForeground": "foreground",
      "HeaderTab.unselectedBackground": "mainColor",
      "HeaderTab.unselectedForeground": "foreground",
      "HeaderTab.underlineColor": "underlineColor",
      "HeaderTab.underlineHeight": 2,
      "HeaderTab.hoverBackground": "hoverColor",
      "HeaderTab.pressedBackground": "pressedColor",
      "HeaderTab.activeForeground": "foreground"
    },
    "ToolWindow.Header.foreground": "foreground",
    "ToolWindow.HeaderTab.selectedForeground": "selectedForeground",
    "ToolWindow.HeaderTab.unselectedBackground": "mainColor",
    "ToolWindow.HeaderTab.unselectedForeground": "foreground",
    "ToolWindow.HeaderTab.underlineColor": "underlineColor",
    "ToolWindow.HeaderTab.underlineHeight": 2,
    "ToolWindow.HeaderTab.hoverBackground": "hoverColor",
    "ToolWindow.HeaderTab.pressedBackground": "pressedColor",
    "Tabs.background": "mainColor",
    "Tabs.foreground": "foreground",
    "Tabs.selectedBackground": "selectedColor",
    "Tabs.selectedForeground": "selectedForeground",
    "Tabs.hoverBackground": "hoverColor",
    "Tabs.pressedBackground": "pressedColor",
    "Tabs.activeBackground": "activeTabBackground",
    "Tabs.activeForeground": "activeTabForeground",
    "ToolWindow.HeaderTab.activeForeground": "foreground",
    "MenuItem.hoverForeground": "foreground",
    "MenuItem.pressedBackground": "pressedColor",
    "MenuItem.pressedForeground": "foreground",
    "MenuItem.selectedBackground": "selectedColor",
    "MenuBar.background": "mainColor",
    "Panel.borderColor": "borderColor"
  }
}